{
"%@% GROWN": "%@% 成長",
"%lld / %lld xp": "%lld / %lld xp",
"%lld day": "%lld日",
"%lld days active": "%lld日間アクティブ",
"%lld keepsakes · this year": "%lld個の宝物 · 今年",
"%lld memories": "%lld個の思い出",
"%lld notes": "%lld枚のメモ",
"%lld of %@ days gathered": "%@日のうち%lld日集まった",
"%lld of %lld": "%lld / %lld",
"%lld/%@": "%lld/%@",
"%lld/10": "%lld/10",
"%lld/150": "%lld/150",
"+ add a keepsake": "+ 宝物を追加",
"30 notes milestone!": "メモ30枚達成！",
"4 minutes of breathing activates your body's calm response. dino will guide you through it.": "4分の呼吸で、からだの落ち着く反応が動きだすよ。ディノが案内するね。",
"THIS SEASON": "今シーズン",
"a few gentle nudges": "やさしいお知らせを少しだけ",
"a few questions to understand how you've been": "最近のあなたを知るための、いくつかの質問",
"a gentle companion travels well": "やさしい相棒は旅上手",
"a gentle note": "やさしいメモ",
"a gentle nudge, not a scoreboard": "スコアボードじゃなくて、やさしい合図",
"a quiet week in the log. no pressure 🌿": "記録は静かな一週間。あせらなくていいよ 🌿",
"a small paragraph of body text showing how it reads at this size. kindness grows in quiet minutes.": "この大きさで読んだときの見え方のための小さな段落。やさしさは静かな時間に育つよ。",
"a soft reminder each evening": "毎晩のやわらかなリマインダー",
"about you": "あなたについて",
"add a little something about yourself": "あなたのことを少しだけ教えて",
"afternoon": "午後",
"all quiet here": "ここは静かだよ",
"allow location access so dino can match its theme to the weather around you.": "位置情報を許可すると、ディノがまわりの天気にテーマを合わせられるよ。",
"ambient sounds": "環境音",
"appearance": "外観",
"apply theme": "テーマを適用",
"avg energy": "平均エネルギー",
"back": "戻る",
"backdate entry": "日付をさかのぼって記録",
"begin": "はじめる",
"begin check-in →": "チェックインをはじめる →",
"begin · %lld min": "はじめる · %lld分",
"bloom": "開花",
"breathe": "呼吸する",
"breathe again": "もう一度呼吸する",
"budding": "つぼみ",
"calendar access needed": "カレンダーへのアクセスが必要",
"calendar connected 🗓️": "カレンダー連携済み 🗓️",
"cancel": "キャンセル",
"change the words": "言葉を変える",
"check-in time": "チェックインの時間",
"checking weather...": "天気を確認中...",
"choose a rhythm": "リズムを選ぶ",
"choose a theme": "テーマを選ぶ",
"choose from library": "ライブラリから選ぶ",
"clear": "晴れ",
"clear all": "すべて消す",
"clear all notifications?": "通知をすべて消す？",
"clear everything": "すべて消す",
"close": "閉じる",
"coming soon": "近日公開",
"confirm it's you": "本人確認",
"connect apple health": "apple healthと連携",
"connect your calendar": "カレンダーと連携",
"continue": "つづける",
"continue with apple": "appleでつづける",
"continue with google": "googleでつづける",
"couldn't delete account": "アカウントを削除できなかった",
"current build": "現在のビルド",
"current streak": "現在の連続記録",
"cycle %@ of %lld": "サイクル %@ / %lld",
"day": "日",
"days": "日",
"deep work done. take a breath.": "集中作業おつかれさま。ひと息ついてね。",
"delete": "削除",
"delete forever": "完全に削除",
"delete this entry?": "この記録を削除する？",
"develop": "現像する",
"dino can learn from your sleep": "ディノはあなたの睡眠から学べるよ",
"dino can notice your movement too": "ディノはあなたの動きにも気づけるよ",
"dino is painting your month...": "ディノがあなたのひと月を描いてる...",
"dino now gently understands your sleep, your movement, and your moments. it learns your rhythms, only ever compares you to you, and knows when to speak and when to just be there": "ディノはあなたの睡眠、動き、瞬間をやさしく理解するようになったよ。あなたのリズムを学んで、比べるのはいつも過去のあなたとだけ。話しかけるときと、そっとそばにいるときを知ってる",
"dino will help you stay on top of your tasks.": "ディノがタスクの管理を手伝うよ。",
"dino world": "ディノワールド",
"done": "完了",
"drop it in ↓": "ここに入れてね ↓",
"each painting is a month of your inner world": "一枚の絵は、あなたの内側のひと月",
"emotional dna": "感情のdna",
"enable notifications": "通知をオンにする",
"enable wind down": "おやすみ時間をオンにする",
"end your day with kindness": "一日をやさしさで締めくくろう",
"enjoying dino?": "ディノを楽しんでる？",
"enter the forest →": "森に入る →",
"evening": "夜",
"find my breath 🌿": "呼吸を見つける 🌿",
"find my light 🦕": "光を見つける 🦕",
"finding the right breath for you…": "あなたに合う呼吸を探してる…",
"finds gentle patterns · off by default": "やさしいパターンを見つける · 初期設定はオフ",
"focus": "集中",
"focus again": "もう一度集中する",
"from": "から",
"from: ": "差出人: ",
"gentle reminders": "やさしいリマインダー",
"gentle reminders?": "やさしいリマインダーは？",
"gentle suggestions": "やさしい提案",
"good to hear that! Dino will help you keep things up.": "よかった！その調子でいけるようディノが手伝うよ。",
"got it! we'll be in touch 🌿": "受け取ったよ！また連絡するね 🌿",
"gratitude jar": "感謝のびん",
"growing": "成長中",
"health access needed": "ヘルスケアへのアクセスが必要",
"health connected 🌿": "ヘルスケア連携済み 🌿",
"health connected!": "ヘルスケア連携完了！",
"hello,": "こんにちは、",
"hold to pause 🌿": "長押しで一時停止 🌿",
"hours vary": "時間はさまざま",
"how did you hear about us?": "ディノをどこで知った？",
"how you've been feeling over time": "これまでの気分の流れ",
"include routines": "ルーティンを含める",
"journal": "日記",
"keep it close 🌱": "そばに置いてね 🌱",
"last 8 weeks of mood + assessments": "直近8週間の気分とチェック",
"last updated: april 2026": "最終更新: 2026年4月",
"let dino learn from your journal": "ディノに日記から学ばせる",
"let's begin": "はじめよう",
"level %lld": "レベル %lld",
"lighter sleep lately tends to make %llds feel heavier.": "最近の浅い眠りは、一日を重たく感じさせがちだよ。",
"location access needed": "位置情報へのアクセスが必要",
"log this feeling": "この気分を記録する",
"logged 🌱": "記録したよ 🌱",
"make it comfortable to read": "読みやすい大きさにしよう",
"mark all read": "すべて既読にする",
"maybe later": "また今度",
"meditate": "瞑想する",
"meditate again": "もう一度瞑想する",
"member since %@": "%@から利用中",
"mood: %@": "気分: %@",
"morning": "朝",
"move this memory": "この思い出を移動する",
"my little": "わたしの小さな",
"new features waiting for you": "新しい機能が待ってるよ",
"next": "次へ",
"no memories yet": "まだ思い出がないよ",
"not much written down this week. weeks like that happen, and that's okay": "今週はあまり書かれなかったね。そういう週もあるし、それでいいんだよ",
"not now": "今はしない",
"notifications": "通知",
"notifications are off": "通知はオフになってる",
"nudge me at": "お知らせの時間",
"off": "オフ",
"offline summary": "オフラインのまとめ",
"okay": "わかった",
"on a heavy day, once in a while, dino offers one soft thing. a playlist, a comfort film, a cozy game. never a feed, always a friend": "重たい日には、ときどきディノがひとつだけやわらかいものを差し出すよ。プレイリスト、心安らぐ映画、あたたかいゲーム。フィードじゃなくて、いつでも友だちとして",
"open settings": "設定を開く",
"or": "または",
"or tell dino in your words…": "またはあなたの言葉でディノに話してね…",
"out of 100": "100点満点中",
"painting will be ready soon 🎨": "絵はもうすぐできるよ 🎨",
"paused": "一時停止中",
"people who do this 3x a week report feeling more grounded": "週3回つづけた人は、心が安定したと感じているよ",
"personal intelligence": "パーソナルインテリジェンス",
"pick a time:": "時間を選んでね:",
"pick the day it belongs to": "この記録の日を選んでね",
"pick the day you want this memory to belong to": "この思い出をどの日にするか選んでね",
"picking the best light...": "いちばんいい光を選んでる...",
"preview": "プレビュー",
"privacy policy": "プライバシーポリシー",
"profile details": "プロフィール詳細",
"question %@ of %lld": "質問 %@ / %lld",
"quick palette": "クイックパレット",
"quiet skies so far. check back soon 🌿": "今のところ空は静か。また見にきてね 🌿",
"quieter care": "より静かなケア",
"rain outside your window means rain in the garden now. dino's world breathes with yours": "窓の外の雨は、庭の雨。ディノの世界はあなたの世界と一緒に呼吸してる",
"rain, forest, soft piano": "雨、森、やわらかなピアノ",
"rate now": "今すぐ評価",
"rate on the app store": "app storeで評価する",
"ready": "準備ok",
"real weather in dino's world": "ディノの世界に本物の天気",
"recent memories": "最近の思い出",
"reminders enabled!": "リマインダーをオンにしたよ！",
"remove": "取り除く",
"report": "報告",
"report this lantern": "このランタンを報告",
"report this lantern?": "このランタンを報告する？",
"reset to default": "初期設定に戻す",
"save": "保存",
"saved": "保存したよ",
"saved to camera roll ✨": "カメラロールに保存したよ ✨",
"scrapbook": "スクラップブック",
"see all —\n%lld memories →": "すべて見る、\n%lld個の思い出 →",
"see your wellness trend": "ウェルネスの流れを見る",
"seed": "たね",
"self-care": "セルフケア",
"self-care reminders": "セルフケアのリマインダー",
"send it →": "送る →",
"send us a note 🦕": "メッセージを送ってね 🦕",
"send →": "送信 →",
"session complete": "セッション完了",
"session length": "セッションの長さ",
"settings": "設定",
"share": "シェア",
"show me": "見せて",
"show my moments": "わたしの瞬間を見せて",
"sign in": "サインイン",
"sign out": "サインアウト",
"sign up": "登録する",
"size": "サイズ",
"skip": "スキップ",
"skip →": "スキップ →",
"sleep affects how you feel more than almost anything else. if you share it, dino can factor it into your patterns and give you a heads up before rough days.\n\nyour health data never leaves your device.": "睡眠は、ほかの何よりも気分に影響するよ。共有してくれたら、ディノはそれをパターンに含めて、大変な日の前にそっと知らせられる。\n\nあなたの健康データがこの端末から出ることはないよ。",
"smarter check ins that know when you slept short, and nudges that lean gentler on heavy days": "眠りが短かった日をわかってくれるチェックインと、重たい日にはよりやさしくなるお知らせ",
"sorry to hear what's going on. what's been weighing on you most?": "大変なんだね。いちばん重たく感じているのはどんなこと？",
"sprout": "芽",
"start logging your mood to see your journey": "気分の記録をはじめると、あなたの道のりが見えてくるよ",
"start over": "やり直す",
"step %@ of %lld": "ステップ %@ / %lld",
"steps": "歩数",
"steps today": "今日の歩数",
"stillness found.": "静けさを見つけた。",
"support resources": "サポートの窓口",
"take photo": "写真を撮る",
"tap a card to flip": "カードをタップしてめくる",
"tap refresh to load weather": "更新をタップして天気を読み込む",
"tap the mic to record your first": "マイクをタップして最初の録音をしてね",
"tap to change photo": "タップして写真を変える",
"tap to open": "タップして開く",
"tap to rate": "タップして評価",
"test notifications": "通知をテスト",
"text entry": "テキスト入力",
"text size": "文字サイズ",
"thank you for being honest/brave. i know it isn't easy to talk about your struggles. let's get started!": "正直に、勇気を出して話してくれてありがとう。つらいことを言葉にするのは簡単じゃないよね。さあ、はじめよう！",
"the evening is arriving early": "今日は夜が早く来るみたい",
"the forest": "森",
"theme is controlled by weather. switch to manual to choose your own.": "テーマは天気が決めてるよ。自分で選ぶには手動に切り替えてね。",
"theme mode": "テーマモード",
"theme: %@": "テーマ: %@",
"there are no wrong answers 🌿": "まちがった答えはないよ 🌿",
"this can't be undone.": "これは元に戻せないよ。",
"this is a reflection tool, not a clinical diagnosis.": "これはふりかえりの道具で、医学的な診断ではないよ。",
"this takes about 3 minutes": "3分くらいかかるよ",
"this week": "今週",
"this week's reflection": "今週のふりかえり",
"this will delete all your moods, journals and gratitude. are you sure?": "気分、日記、感謝の記録がすべて削除されるよ。本当にいい？",
"this will permanently delete your account, all your data from the cloud, and sign you out. this cannot be undone. are you sure?": "アカウントとクラウド上のすべてのデータが完全に削除されて、サインアウトされるよ。元に戻せないけど、本当にいい？",
"time": "時間",
"to enable notifications, go to Settings → Dino → Notifications and turn them on": "通知をオンにするには、設定 → dino → 通知 から有効にしてね",
"to permanently delete your account, please verify your identity.": "アカウントを完全に削除するには、本人確認をしてね。",
"to receive self-care reminders, enable notifications for Dino in iPhone Settings → Notifications → Dino": "セルフケアのリマインダーを受け取るには、iphoneの設定 → 通知 → dino で通知をオンにしてね",
"to: ": "宛先: ",
"today": "今日",
"today I...": "今日、わたしは...",
"today's focus": "今日のフォーカス",
"try again a little later 🌿": "少しあとでもう一度試してね 🌿",
"update": "アップデート",
"used by people before meetings, after hard news, during panic moments": "会議の前、つらい知らせのあと、パニックの瞬間に使われているよ",
"version": "バージョン",
"view report": "レポートを見る",
"waiting on sleep data 🌙": "睡眠データを待ってるよ 🌙",
"want to tell me what's going on?": "何があったか、話してみる？",
"want to write about your day?": "今日のことを書いてみる？",
"water, food": "水、ごはん",
"we didn't cross paths much this week. the door is always open 🌱": "今週はあまり会えなかったね。扉はいつでも開いてるよ 🌱",
"we read every message": "メッセージはすべて読んでるよ",
"weather themes": "天気テーマ",
"weekly check-in": "週間チェックイン",
"well done": "おつかれさま",
"what others are saying": "みんなの声",
"what should we call you?": "なんて呼べばいい？",
"what's new in dino": "ディノの新機能",
"what's on your mind?": "何を考えてる？",
"whatever's on your mind…": "思っていること、なんでも…",
"when anxiety hits": "不安が来たとき",
"while receiving professional care is important, small habits and lifestyle changes can make a stark difference.": "専門的なケアを受けることは大切だけど、小さな習慣や暮らしの変化も大きな違いを生むよ。",
"wind down": "おやすみ時間",
"wind-down": "おやすみ時間",
"yes, hold that time 🌿": "うん、その時間をおさえておいて 🌿",
"you": "あなた",
"you completed this week ✓": "今週をやりきったね ✓",
"you showed up ": "ちゃんと来たね ",
"you showed up every single day.\nnow go stick your notes on your real mirror\nand take a picture 🪞": "毎日ちゃんと来たね。\n今度は本物の鏡にメモを貼って\n写真を撮ってみて 🪞",
"you took time for yourself.": "自分のための時間をとったね。",
"you'll be asked to sign in with apple again.": "もう一度appleでのサインインを求められるよ。",
"you'll be asked to sign in with google again.": "もう一度googleでのサインインを求められるよ。",
"your %@ painting is ready ✨": "%@の絵ができたよ ✨",
"your busiest day this week 🌿": "今週いちばん忙しかった日 🌿",
"your calendar looks full for now.": "今のところカレンダーはいっぱいみたい。",
"your emotional gallery": "あなたの感情ギャラリー",
"your first painting generates at the end of this month 🎨": "最初の絵は今月の終わりにできるよ 🎨",
"your iphone can gather little moments privately. a photo you took, a place you visited, a song you played. your iphone shows them only to you first. dino sees just the one moment you choose to write about, and only then. nothing is shared or sent anywhere.": "iphoneは小さな瞬間をプライベートに集められるよ。撮った写真、訪れた場所、聴いた曲。まずあなただけに見せる。ディノが見るのは、あなたが書くと決めたひとつの瞬間だけ、そのときだけ。どこにも共有されたり送られたりしないよ。",
"your journal entries will live here once you start writing.": "書きはじめたら、日記はここに集まっていくよ。",
"your mirror": "あなたの鏡",
"your mirror is full ✨": "鏡がいっぱいになったよ ✨",
"your name": "あなたの名前",
"your one stop mental wellness app ❤️": "こころの健やかさをまるごと支えるアプリ ❤️",
"your rating helps us reach more people 🌿": "あなたの評価が、もっと多くの人に届く力になるよ 🌿",
"your rhythms": "あなたのリズム",
"your streaks": "あなたの連続記録",
"your week %lld report": "第%lld週のレポート",
"your wellness journey": "あなたのウェルネスの道のり",
"“%@”": "「%@」",
"✦ still forming": "✦ まだかたちになる途中",
"✦ suggested": "✦ おすすめ"
}
